enp/__init__.py
enp/core/__init__.py
enp/core/network.py
enp/core/neuron.py
enp/evolution/__init__.py
enp/evolution/mutator.py
enp/learning/__init__.py
enp/learning/trainer.py
enp/memory/__init__.py
enp/memory/trace_memory.py
enp_ai-0.1.0.dist-info/METADATA
enp_ai-0.1.0.dist-info/WHEEL
enp_ai-0.1.0.dist-info/top_level.txt
enp_ai-0.1.0.dist-info/RECORD
